kinesis/__init__.py
kinesis/consumer.py
kinesis/exceptions.py
kinesis/producer.py
kinesis/state.py
kinesis_python-0.2.0.dist-info/LICENSE
kinesis_python-0.2.0.dist-info/METADATA
kinesis_python-0.2.0.dist-info/WHEEL
kinesis_python-0.2.0.dist-info/top_level.txt
kinesis_python-0.2.0.dist-info/RECORD
