Metadata-Version: 2.1
Name: kinesis-python
Version: 0.2.0
Summary: Low level, multiprocessing based AWS Kinesis producer & consumer library
Home-page: https://github.com/NerdWalletOSS/kinesis-python
Author: Evan Borgstrom
Author-email: eborgstrom@nerdwallet.com
License: Apache License Version 2.0
Platform: UNKNOWN
Classifier: Development Status :: 4 - Beta
Classifier: Intended Audience :: Developers
Classifier: License :: OSI Approved :: Apache Software License
Classifier: Natural Language :: English
Classifier: Programming Language :: Python
Classifier: Topic :: Internet
Classifier: Topic :: Software Development :: Libraries
Requires-Dist: boto3 (<2.0,>=1.4.4)
Requires-Dist: offspring (<1.0,>=0.0.3)
Requires-Dist: six (<2.0,>=1.11.0)
